{"last_updated_timestamp":"2025-12-01T10:12:48.428Z","total_power_consumption_watts":491,"login_nodes":[{"node_name":"cloud-244","cores_total":64,"mem_total_gb":1008,"cpu_util_percent":0,"mem_util_percent":3.1700980665634995,"active_users":0,"active_usernames":[]},{"node_name":"cloud-248","cores_total":64,"mem_total_gb":504,"cpu_util_percent":0,"mem_util_percent":5.875412864875034,"active_users":3,"active_usernames":["dt89","pr35"]}],"gpu_nodes":[{"node_name":"cloud-243","cores_total":128,"mem_total_gb":1008,"cpu_util_percent":0,"mem_util_percent":44.13836627017006,"gpu_summary_name":"NVIDIA RTX 6000","gpus":[{"gpu_id":0,"gpu_name":"NVIDIA A100 80GB PCIe","utilization_percent":0,"memory_used_mib":23032,"memory_total_mib":81920,"temperature_celsius":42,"power_draw_watts":68.7,"power_limit_watts":300},{"gpu_id":1,"gpu_name":"Tesla T4","utilization_percent":0,"memory_used_mib":6808,"memory_total_mib":15360,"temperature_celsius":36,"power_draw_watts":27.7,"power_limit_watts":70}],"active_users":10,"active_usernames":["apl11","cle15","dd03","dt89","ef21","jz86"]},{"node_name":"cloud-247","cores_total":128,"mem_total_gb":1134,"cpu_util_percent":0,"mem_util_percent":6.237129899946208,"gpu_summary_name":"NVIDIA RTX 6000","gpus":[{"gpu_id":0,"gpu_name":"NVIDIA H100 NVL","utilization_percent":95,"memory_used_mib":46923,"memory_total_mib":95830,"temperature_celsius":75,"power_draw_watts":394.78,"power_limit_watts":400}],"active_users":14,"active_usernames":["apl11","dd03","ds77","jh92","rr20","sd68","ts48"]}]}